README.txt
setup.py
collective/__init__.py
collective.contentrules.talesaction.egg-info/PKG-INFO
collective.contentrules.talesaction.egg-info/SOURCES.txt
collective.contentrules.talesaction.egg-info/dependency_links.txt
collective.contentrules.talesaction.egg-info/entry_points.txt
collective.contentrules.talesaction.egg-info/namespace_packages.txt
collective.contentrules.talesaction.egg-info/not-zip-safe
collective.contentrules.talesaction.egg-info/requires.txt
collective.contentrules.talesaction.egg-info/top_level.txt
collective/contentrules/__init__.py
collective/contentrules/talesaction/__init__.py
collective/contentrules/talesaction/action.py
collective/contentrules/talesaction/configure.zcml
collective/contentrules/talesaction/tests.py
collective/contentrules/talesaction/version.txt
collective/contentrules/talesaction/locales/collective.contentrules.talesaction.pot
collective/contentrules/talesaction/locales/plone.pot
collective/contentrules/talesaction/locales/update.sh
collective/contentrules/talesaction/locales/fr/LC_MESSAGES/collective.contentrules.talesaction.po
collective/contentrules/talesaction/locales/fr/LC_MESSAGES/plone.po
docs/HISTORY.txt
docs/INSTALL.txt
docs/LICENSE.GPL
docs/LICENSE.txt