Metadata-Version: 1.0
Name: collective.contentrules.talesaction
Version: 1.0
Summary: An add-on to add TALES expression actions in your content rules
Home-page: http://svn.plone.org/svn/collective/
Author: UNKNOWN
Author-email: UNKNOWN
License: GPL
Platform: UNKNOWN
Classifier: Framework :: Plone
Classifier: Programming Language :: Python
